xomx/__init__.py
xomx/classifiers/ExtraTrees.py
xomx/classifiers/__init__.py
xomx/classifiers/multiclass.py
xomx/data_importation/__init__.py
xomx/data_importation/gdc.py
xomx/embeddings/BetaVAE.py
xomx/embeddings/__init__.py
xomx/feature_selection/RFEExtraTrees.py
xomx/feature_selection/__init__.py
xomx/plotting/__init__.py
xomx/plotting/basic_plot.py
xomx/tools/__init__.py
xomx/tools/bio.py
xomx/tools/utils.py
xomx-0.1.16.dist-info/LICENSE
xomx-0.1.16.dist-info/METADATA
xomx-0.1.16.dist-info/WHEEL
xomx-0.1.16.dist-info/top_level.txt
xomx-0.1.16.dist-info/RECORD
