Metadata-Version: 2.1
Name: xomx
Version: 0.1.16
Summary: xomx: a python library for computational omics
Home-page: https://github.com/perrin-isir/xomx
Author: Nicolas Perrin-Gilbert
License: LICENSE
License-File: LICENSE
Requires-Dist: pandas <=2.1.0,>=1.3.0
Requires-Dist: numpy >=1.21.1
Requires-Dist: anndata >=0.7.6
Requires-Dist: scipy >=1.4.1
Requires-Dist: matplotlib >=3.1.3
Requires-Dist: scikit-learn >=0.24.2
Requires-Dist: joblib >=1.0.1
Requires-Dist: requests >=2.23.0
Requires-Dist: holoviews >=1.17.1
Requires-Dist: bokeh >=3.2.2
Requires-Dist: leidenalg >=0.8.8
Requires-Dist: jax >=0.3.23
Requires-Dist: optax >=0.1.2
Requires-Dist: flax >=0.6.3
